mashup/102003619.py
mashup/__init__.py
mashup/__main__.py
Mashup_Pulkit_102003619-1.0.1.dist-info/LICENSE
Mashup_Pulkit_102003619-1.0.1.dist-info/METADATA
Mashup_Pulkit_102003619-1.0.1.dist-info/WHEEL
Mashup_Pulkit_102003619-1.0.1.dist-info/entry_points.txt
Mashup_Pulkit_102003619-1.0.1.dist-info/top_level.txt
Mashup_Pulkit_102003619-1.0.1.dist-info/RECORD
