Metadata-Version: 2.1
Name: Mashup-Pulkit-102003619
Version: 1.0.1
Summary: A Python program that allows user to create mashup of audios which are extracted from youtube videos requested singer
Home-page: https://github.com/Pulkit0103
Author: Pulkit
Author-email: girdhar.pulkit.2002@gmail.com
License: MIT
Classifier: License :: OSI Approved :: MIT License
Classifier: Programming Language :: Python :: 3.6
Classifier: Programming Language :: Python :: 3.7
Classifier: Programming Language :: Python :: 3.8
Classifier: Programming Language :: Python :: 3.9
Classifier: Programming Language :: Python :: 3.10
Classifier: Programming Language :: Python :: 3.11
License-File: LICENSE
Requires-Dist: pathlib
Requires-Dist: numpy
Requires-Dist: pandas
Requires-Dist: pydub
Requires-Dist: pytube
